numistalib/__init__.py
numistalib/__main__.py
numistalib/client.py
numistalib/config.py
numistalib/cli/__init__.py
numistalib/cli/catalogues.py
numistalib/cli/collections.py
numistalib/cli/config.py
numistalib/cli/image_search.py
numistalib/cli/issuers.py
numistalib/cli/issues.py
numistalib/cli/literature.py
numistalib/cli/main.py
numistalib/cli/mints.py
numistalib/cli/prices.py
numistalib/cli/theme.py
numistalib/cli/types.py
numistalib/cli/users.py
numistalib/models/__init__.py
numistalib/models/catalogues.py
numistalib/models/collections.py
numistalib/models/currency.py
numistalib/models/errors.py
numistalib/models/issuer.py
numistalib/models/issues.py
numistalib/models/literature.py
numistalib/models/mints.py
numistalib/models/prices.py
numistalib/models/references.py
numistalib/models/types.py
numistalib/models/updates.py
numistalib/models/users.py
numistalib/models/base/__init__.py
numistalib/models/base/base_model.py
numistalib/services/__init__.py
numistalib/services/base/__init__.py
numistalib/services/base/helpers.py
numistalib/services/base/service.py
numistalib/services/catalogues/__init__.py
numistalib/services/catalogues/base.py
numistalib/services/catalogues/service.py
numistalib/services/collections/__init__.py
numistalib/services/collections/base.py
numistalib/services/collections/service.py
numistalib/services/image_search/__init__.py
numistalib/services/image_search/base.py
numistalib/services/image_search/service.py
numistalib/services/issuer/__init__.py
numistalib/services/issuer/base.py
numistalib/services/issuer/service.py
numistalib/services/issues/__init__.py
numistalib/services/issues/base.py
numistalib/services/issues/service.py
numistalib/services/literature/__init__.py
numistalib/services/literature/base.py
numistalib/services/literature/service.py
numistalib/services/mints/__init__.py
numistalib/services/mints/base.py
numistalib/services/mints/service.py
numistalib/services/prices/__init__.py
numistalib/services/prices/base.py
numistalib-0.1.2.dist-info/METADATA
numistalib-0.1.2.dist-info/WHEEL
numistalib-0.1.2.dist-info/entry_points.txt
numistalib-0.1.2.dist-info/RECORD
