Metadata-Version: 2.4
Name: numistalib
Version: 0.1.2
Summary: Numista API wrapper
Project-URL: Homepage, https://github.com/wells01440/numistalib
Project-URL: Documentation, https://numistalib.readthedocs.io/
Project-URL: Source, https://github.com/wells01440/numistalib
Project-URL: Issues, https://github.com/wells01440/numistalib/issues
Project-URL: Changelog, https://github.com/wells01440/numistalib/blob/main/CHANGELOG
Project-URL: NumistaAPI, https://en.numista.com/api/doc/index.php
Project-URL: NumistaConditions, https://en.numista.com/conditions.php
Project-URL: NumistaLegal, https://en.numista.com/legal.php
Project-URL: NumistaPricingAPI, https://en.numista.com/api/pricing.php
Author-email: Andy Wells <wells10440@gmail.com>
License: MIT
Requires-Python: >=3.13
Requires-Dist: beautifulsoup4>=4.14.3
Requires-Dist: ccy>=1.7.2
Requires-Dist: click>=8.1.0
Requires-Dist: hishel[httpx]>=1.1.6
Requires-Dist: httpx>=0.28.1
Requires-Dist: pycountry>=24.6.1
Requires-Dist: pydantic-settings>=2.5.0
Requires-Dist: pydantic>=2.12.5
Requires-Dist: pyrate-limiter>=3.9.0
Requires-Dist: rich>=14.2.0
Requires-Dist: tenacity>=9.0.0
Requires-Dist: textual-image>=0.8.5
